Metadata-Version: 2.1
Name: named-array
Version: 0.11
Summary: This is a python module that extends numpy array to be able to have column names to index with
Home-page: https://github.com/Rainbow-Dreamer/named_array
Author: Rainbow-Dreamer
Author-email: 1036889495@qq.com
License: LGPLv2.1
Download-URL: https://github.com/Rainbow-Dreamer/named_array/archive/0.11.tar.gz
Keywords: python,hide warnings
Platform: UNKNOWN
Classifier: Development Status :: 3 - Alpha
Classifier: Intended Audience :: Developers
Classifier: Topic :: Software Development :: Build Tools
Classifier: License :: OSI Approved :: GNU Lesser General Public License v2 or later (LGPLv2+)
Classifier: Programming Language :: Python :: 3.6
Classifier: Programming Language :: Python :: 3.7
Classifier: Programming Language :: Python :: 3.8
Classifier: Programming Language :: Python :: 3.9
Classifier: Programming Language :: Python :: 3.10
License-File: LICENSE
